Metadata-Version: 2.4
Name: x_4357_make_who_is_John_Connor_x
Version: 0.20.17
Summary: Helper scripts that automate the 'Who is John Connor?' Copilot CLI workflow and expose a persona vetting service adapter.
Author-email: "RRGM (Software Tech Lead, Primus Pilus Night Watch AI Corp.)" <foo@bar.com>
Requires-Python: >=3.8
